optimism/__init__.py
optimism/optimism.py
optimism/py.typed
optimism/test_examples.py
optimism/examples/a.txt
optimism/examples/b.txt
optimism/examples/bad.py
optimism/examples/basic.py
optimism/examples/bits.py
optimism/examples/block.py
optimism/examples/catch_and_release.py
optimism/examples/code.py
optimism/examples/core.py
optimism/examples/doc_example.py
optimism/examples/doctests.py
optimism/examples/errors.py
optimism/examples/files.py
optimism/examples/fragments.py
optimism/examples/io_example.py
optimism/examples/literals.py
optimism/examples/memoryReports.py
optimism/examples/multi.py
optimism/examples/reverse_tracing.py
optimism/examples/runfile.py
optimism/examples/skip.py
optimism/examples/structure.py
optimism/examples/suites.py
optimism/examples/tracing.py
optimism-3.1.3.dist-info/LICENSE.txt
optimism-3.1.3.dist-info/METADATA
optimism-3.1.3.dist-info/WHEEL
optimism-3.1.3.dist-info/top_level.txt
optimism-3.1.3.dist-info/RECORD
