Metadata-Version: 2.1
Name: optimism
Version: 3.1.3
Summary: Very simple testing framework suitable for beginner programmers, with easy functions for accomplishing most common testing tasks like providing input. Requires Python 3.8+.
Home-page: https://cs.wellesley.edu/~pmwh/optimism/docs/optimism.html
Author: Peter Mawhorter
Author-email: pmawhort@wellesley.edu
License: BSD 3-Clause License
Classifier: Programming Language :: Python :: 3 :: Only
Classifier: Development Status :: 4 - Beta
Classifier: Intended Audience :: Education
Classifier: Intended Audience :: Developers
Classifier: License :: OSI Approved :: BSD License
Classifier: Operating System :: OS Independent
Classifier: Natural Language :: English
Classifier: Topic :: Education
Requires-Python: >=3.8
License-File: LICENSE.txt
Provides-Extra: test
Requires-Dist: pytest; extra == "test"
